wibeee/__init__.py
wibeee/utils.py
wibeee/wibeee.py
wibeee/errors/__init__.py
wibeee-1.2.0.dist-info/LICENSE
wibeee-1.2.0.dist-info/METADATA
wibeee-1.2.0.dist-info/WHEEL
wibeee-1.2.0.dist-info/top_level.txt
wibeee-1.2.0.dist-info/RECORD
