Metadata-Version: 2.1
Name: wibeee
Version: 1.2.0
Summary: An api interface for WiBeee
Home-page: https://github.com/veryheavypickle/wibeee
Author: Yoda
Author-email: dev-yoda@proton.me
Project-URL: Github, https://github.com/veryheavypickle/wibeee
Classifier: Programming Language :: Python :: 3
Classifier: License :: OSI Approved :: GNU General Public License v3 (GPLv3)
Classifier: Operating System :: OS Independent
Requires-Python: >=3.6
License-File: LICENSE
